folix.py
folix-1.0.1.dist-info/METADATA
folix-1.0.1.dist-info/WHEEL
folix-1.0.1.dist-info/entry_points.txt
folix-1.0.1.dist-info/top_level.txt
folix-1.0.1.dist-info/RECORD
