Metadata-Version: 2.4
Name: folix
Version: 1.0.1
Summary: A smart PDF splitter that uses AI to extract chapters.
Home-page: https://github.com/basit-ayub/folix
Author: Abdul Basit
Author-email: a.basitayub2004@gmail.com
License: MIT
Classifier: Programming Language :: Python :: 3
Classifier: Operating System :: OS Independent
Requires-Python: >=3.7
Requires-Dist: pymupdf
Requires-Dist: mistralai
Dynamic: author
Dynamic: author-email
Dynamic: classifier
Dynamic: description
Dynamic: description-content-type
Dynamic: home-page
Dynamic: license
Dynamic: requires-dist
Dynamic: requires-python
Dynamic: summary
